Anapass/ANA6707.py
Anapass/ANA6708.py
Anapass/Adc.py
Anapass/Aging.py
Anapass/FlashMemory.py
Anapass/Register.py
Anapass/TDeviceAndroid.py
Anapass/TDeviceBase.py
Anapass/TDeviceWin.py
Anapass/TDeviceWinDLL.py
Anapass/TModule.py
Anapass/Util.py
Anapass/__init__.py
Anapass/ANA6705/ANA6705_FlashMipiToSpi.py
Anapass/ANA6705/__init__.py
Anapass/ANA6706/ANA6706_FlashMipiToSpi.py
Anapass/ANA6706/__init__.py
Anapass/AppShell/AppClass.py
Anapass/AppShell/CommandTFlash.py
Anapass/AppShell/Main.py
Anapass/AppShell/__init__.py
Anapass/Database/TESysDB.py
Anapass/Database/__init__.py
Anapass/Database/Lib/__init__.py
Anapass/Database/Lib/Single/Table.py
Anapass/Database/Lib/Single/__init__.py
Anapass/Database/TESys/__init__.py
Anapass/Database/TESys/Join/TcStepList.py
Anapass/Database/TESys/Join/__init__.py
Anapass/Database/TESys/Single/DutPcb.py
Anapass/Database/TESys/Single/Hardware.py
Anapass/Database/TESys/Single/Sc.py
Anapass/Database/TESys/Single/SocPcb.py
Anapass/Database/TESys/Single/Tc.py
Anapass/Database/TESys/Single/__init__.py
Anapass/Example/ALL_REG_READ.py
Anapass/Example/CatchPower.py
Anapass/Example/FileTransfer.py
Anapass/Example/ReadChipID.py
Anapass/Example/RegReadWriteVerify.py
Anapass/Example/RegisterPrint.py
Anapass/Example/ResetNext.py
Anapass/Example/SendTxtCmd.py
Anapass/Example/T5-OTP_DUMP_BANK.py
Anapass/Example/T5_current.py
Anapass/Example/TDeviceBasicTest.py
Anapass/Example/Test_RREG1_WREG1.py
Anapass/Example/__init__.py
Anapass/Example/FlashMemory/DataWriteRead.py
Anapass/Example/FlashMemory/EraseSector.py
Anapass/Example/FlashMemory/ReadStatus.py
Anapass/Example/FlashMemory/__init__.py
anapass_python-2.0.0.15.data/data/AnapassTComm.dll
anapass_python-2.0.0.15.data/data/AnapassTModule.dll
anapass_python-2.0.0.15.data/data/AnapassTParser.dll
anapass_python-2.0.0.15.dist-info/LICENSE
anapass_python-2.0.0.15.dist-info/METADATA
anapass_python-2.0.0.15.dist-info/WHEEL
anapass_python-2.0.0.15.dist-info/top_level.txt
anapass_python-2.0.0.15.dist-info/RECORD
