Metadata-Version: 2.1
Name: anapass-python
Version: 2.0.0.15
Summary: Anapass Python Package
Home-page: http://www.anapass.com
Author: hthwang
Author-email: hthwang@anapass.com
Classifier: Programming Language :: Python :: 3
Classifier: License :: OSI Approved :: MIT License
Classifier: Operating System :: OS Independent
Requires-Python: >=3.6
License-File: LICENSE
